turbot5/__init__.py
turbot5/heads/__init__.py
turbot5/heads/decoder_heds.py
turbot5/heads/encoder_heads.py
turbot5/heads/t5_heads.py
turbot5/model/__init__.py
turbot5/model/attentions.py
turbot5/model/config.py
turbot5/model/modeling.py
turbot5/model/modules.py
turbot5/model/padding.py
turbot5/model/utils.py
turbot5/ops/__init__.py
turbot5/ops/attention_bias.py
turbot5/ops/flash_attention.py
turbot5/ops/flash_decoding.py
turbot5/ops/fused_bias_attention.py
turbot5/ops/gated_mlp.py
turbot5/ops/naive_attention.py
turbot5/ops/rms_norm.py
turbot5/ops/varlen_fused_bias_attn.py
turbot5-0.0.2.dist-info/METADATA
turbot5-0.0.2.dist-info/WHEEL
turbot5-0.0.2.dist-info/RECORD
